graphlearn/__init__.py
graphlearn/pywrap_graphlearn.cpython-38-x86_64-linux-gnu.so
graphlearn/python/graph.py
graphlearn/python/utils.py
graphlearn/python/config.py
graphlearn/python/__init__.py
graphlearn/python/cluster.py
graphlearn/python/server.py
graphlearn/python/errors.py
graphlearn/python/gsl/dag_edge.py
graphlearn/python/gsl/dag_dataset.py
graphlearn/python/gsl/dag.py
graphlearn/python/gsl/dag_node.py
graphlearn/python/gsl/__init__.py
graphlearn/python/lib/libgraphlearn_shared.so
graphlearn/python/data/values.py
graphlearn/python/data/state.py
graphlearn/python/data/decoder.py
graphlearn/python/data/feature_spec.py
graphlearn/python/data/topology.py
graphlearn/python/data/__init__.py
graphlearn/python/sampler/edge_sampler.py
graphlearn/python/sampler/subgraph_sampler.py
graphlearn/python/sampler/negative_sampler.py
graphlearn/python/sampler/__init__.py
graphlearn/python/sampler/node_sampler.py
graphlearn/python/sampler/neighbor_sampler.py
graphlearn/python/sampler/tests/test_in_degree_neighbor_sampling.py
graphlearn/python/sampler/tests/test_node_weight_negavtive_sampling.py
graphlearn/python/sampler/tests/test_random_node_subgraph_sampling.py
graphlearn/python/sampler/tests/test_random_negative_sampling.py
graphlearn/python/sampler/tests/test_random_worepl_neighbor_sampling.py
graphlearn/python/sampler/tests/__init__.py
graphlearn/python/sampler/tests/test_edge_weight_neighbor_sampling.py
graphlearn/python/sampler/tests/test_full_neighbor_sampling.py
graphlearn/python/sampler/tests/test_conditional_negative_sampling.py
graphlearn/python/sampler/tests/test_in_order_node_subgraph_sampling.py
graphlearn/python/sampler/tests/test_random_neighbor_sampling.py
graphlearn/python/sampler/tests/test_topk_neighbor_sampling.py
graphlearn/python/sampler/tests/test_sampling.py
graphlearn/python/sampler/tests/test_in_degree_negavtive_sampling.py
graphlearn/python/nn/dataset.py
graphlearn/python/nn/data.py
graph_learn-1.1.0.dist-info/top_level.txt
graph_learn-1.1.0.dist-info/METADATA
graph_learn-1.1.0.dist-info/RECORD
graph_learn-1.1.0.dist-info/WHEEL
